nr/util/__init__.py
nr/util/algorithm/__init__.py
nr/util/algorithm/longest_common_substring.py
nr/util/annotations/__init__.py
nr/util/atomic/__init__.py
nr/util/atomic/_counter.py
nr/util/awsgi/__init__.py
nr/util/awsgi/_app.py
nr/util/awsgi/_types.py
nr/util/awsgi/launcher/__init__.py
nr/util/awsgi/launcher/flask.py
nr/util/awsgi/launcher/gunicorn.py
nr/util/awsgi/launcher/uvicorn.py
nr/util/chaindict.py
nr/util/config/__init__.py
nr/util/config/_loader.py
nr/util/date/__init__.py
nr/util/date/duration.py
nr/util/date/format.py
nr/util/date/format_sets.py
nr/util/date/options.py
nr/util/digraph/__init__.py
nr/util/digraph/_digraph.py
nr/util/digraph/algorithm/remove_with_predecessors.py
nr/util/digraph/algorithm/topological_sort.py
nr/util/exceptions/__init__.py
nr/util/fs/__init__.py
nr/util/fs/_atomic.py
nr/util/fs/_chmod.py
nr/util/fs/_discovery.py
nr/util/fs/_path.py
nr/util/fs/_walk.py
nr/util/functional/__init__.py
nr/util/functional/_assure.py
nr/util/functional/_coalesce.py
nr/util/functional/_consumer.py
nr/util/functional/_once.py
nr/util/functional/_predicate.py
nr/util/functional/_supplier.py
nr/util/generic/__init__.py
nr/util/git/__init__.py
nr/util/inspect/__init__.py
nr/util/io/__init__.py
nr/util/io/_readers.py
nr/util/iter/__init__.py
nr/util/iter/_sequence_walker.py
nr/util/keyvalue/__init__.py
nr/util/keyvalue/_api.py
nr/util/keyvalue/_mappingadapter.py
nr/util/keyvalue/sqlite.py
nr/util/logging/filters/simple_filter.py
nr/util/logging/formatters/terminal_colors.py
nr/util/once.py
nr/util/optional.py
nr/util/orderedset.py
nr/util/parsing/__init__.py
nr/util/parsing/_scanner.py
nr/util/parsing/_tokenizer/__init__.py
nr/util/parsing/_tokenizer/extractor.py
nr/util/parsing/_tokenizer/ruleset.py
nr/util/parsing/_tokenizer/tokenizer.py
nr/util/parsing/rules.py
nr/util/plugins/__init__.py
nr/util/plugins/_pkg_resources.py
nr/util/plugins/_plugin_registry.py
nr/util/preconditions/__init__.py
nr/util/process/__init__.py
nr/util/process/_pidfile.py
nr_util-0.8.13.dist-info/LICENSE
nr_util-0.8.13.dist-info/METADATA
nr_util-0.8.13.dist-info/WHEEL
nr_util-0.8.13.dist-info/RECORD
